[
    {
        "id": 1386,
        "name": 1386,
        "availability": "2000-01-01T00:00:00.000Z/2000-01-01T00:03:20.000Z",
        "description": "",
        "position": {
            "interpolationAlgorithm": "LAGRANGE",
            "interpolationDegree": 5,
            "referenceFrame": "FIXED",
            "epoch": "2000-01-01T00:00:00.000Z",
            "cartesian": [
                0.0,
                -5226574.0,
                -3655610.0,
                -6733.837890625,
                1.0,
                -5224087.0,
                -3659168.75,
                -1955.29541015625,
                2.0,
                -5221595.0,
                -3662723.75,
                2823.247802734375,
                3.0,
                -5219161.5,
                -3666183.25,
                7601.8115234375,
                4.0,
                -5216658.5,
                -3669730.75,
                12380.328125,
                5.0,
                -5214150.5,
                -3673274.5,
                17158.892578125,
                6.0,
                -5211636.5,
                -3676814.5,
                21937.4453125,
                7.0,
                -5209182.5,
                -3680259.0,
                26715.98828125,
                8.0,
                -5206658.0,
                -3683791.25,
                31494.515625,
                9.0,
                -5204128.5,
                -3687320.0,
                36272.9140625,
                10.0,
                -5201593.5,
                -3690844.75,
                41051.40234375,
                11.0,
                -5199118.0,
                -3694274.25,
                45829.76171875,
                12.0,
                -5196572.5,
                -3697791.25,
                50608.08984375,
                13.0,
                -5194022.0,
                -3701304.5,
                55386.39453125,
                14.0,
                -5191465.5,
                -3704814.0,
                60164.6640625,
                15.0,
                -5188969.5,
                -3708228.25,
                64942.79296875,
                16.0,
                -5186402.5,
                -3711730.0,
                69720.9921875,
                17.0,
                -5183830.5,
                -3715228.0,
                74499.046875,
                18.0,
                -5181253.5,
                -3718722.0,
                79276.9375,
                19.0,
                -5178736.0,
                -3722121.0,
                84054.90625,
                20.0,
                -5176148.5,
                -3725607.25,
                88832.71875,
                21.0,
                -5173555.5,
                -3729089.5,
                93610.3671875,
                22.0,
                -5170957.0,
                -3732568.0,
                98387.96875,
                23.0,
                -5168353.5,
                -3736042.5,
                103165.5078125,
                24.0,
                -5165810.5,
                -3739422.25,
                107942.875,
                25.0,
                -5163196.5,
                -3742889.0,
                112720.1875,
                26.0,
                -5160577.0,
                -3746351.75,
                117497.3359375,
                27.0,
                -5157952.5,
                -3749810.5,
                122274.4140625,
                28.0,
                -5155389.0,
                -3753174.75,
                127051.421875,
                29.0,
                -5152754.0,
                -3756625.5,
                131828.34375,
                30.0,
                -5150114.0,
                -3760072.5,
                136604.109375,
                31.0,
                -5147468.5,
                -3763515.5,
                141380.890625,
                32.0,
                -5144883.5,
                -3766865.5,
                146157.609375,
                33.0,
                -5142228.5,
                -3770299.0,
                150933.125,
                34.0,
                -5139568.0,
                -3773730.25,
                155709.65625,
                35.0,
                -5136902.0,
                -3777157.25,
                160485.015625,
                36.0,
                -5134230.5,
                -3780580.25,
                165261.375,
                37.0,
                -5131619.5,
                -3783910.25,
                170036.546875,
                38.0,
                -5128939.5,
                -3787324.0,
                174811.625,
                39.0,
                -5126252.5,
                -3790735.0,
                179586.609375,
                40.0,
                -5123561.0,
                -3794142.0,
                184361.46875,
                41.0,
                -5120929.5,
                -3797456.25,
                189136.25,
                42.0,
                -5118227.5,
                -3800855.0,
                193910.921875,
                43.0,
                -5115521.5,
                -3804248.5,
                198685.46875,
                44.0,
                -5112809.0,
                -3807639.25,
                203459.921875,
                45.0,
                -5110091.5,
                -3811025.75,
                208233.15625,
                46.0,
                -5107435.0,
                -3814320.0,
                213007.375,
                47.0,
                -5104707.5,
                -3817698.5,
                217780.375,
                48.0,
                -5101975.5,
                -3821071.5,
                222553.234375,
                49.0,
                -5099237.5,
                -3824441.75,
                227325.984375,
                50.0,
                -5096495.0,
                -3827808.0,
                232098.609375,
                51.0,
                -5093813.0,
                -3831082.0,
                236871.109375,
                52.0,
                -5091061.0,
                -3834438.5,
                241643.46875,
                53.0,
                -5088303.0,
                -3837792.5,
                246415.703125,
                54.0,
                -5085539.5,
                -3841142.25,
                251186.6875,
                55.0,
                -5082771.5,
                -3844487.75,
                255958.640625,
                56.0,
                -5079998.0,
                -3847829.0,
                260729.34375,
                57.0,
                -5077287.5,
                -3851077.0,
                265499.90625,
                58.0,
                -5074504.0,
                -3854410.25,
                270270.3125,
                59.0,
                -5071715.5,
                -3857739.25,
                275040.5625,
                60.0,
                -5068922.0,
                -3861064.0,
                279810.71875,
                61.0,
                -5066123.5,
                -3864384.5,
                284579.5625,
                62.0,
                -5063320.0,
                -3867700.75,
                289349.34375,
                63.0,
                -5060579.5,
                -3870924.0,
                294117.875,
                64.0,
                -5057766.0,
                -3874232.0,
                298886.21875,
                65.0,
                -5054947.5,
                -3877535.75,
                303655.53125,
                66.0,
                -5052124.0,
                -3880835.5,
                308422.4375,
                67.0,
                -5049295.5,
                -3884130.75,
                313190.3125,
                68.0,
                -5046462.0,
                -3887421.75,
                317958.0,
                69.0,
                -5043623.5,
                -3890708.75,
                322724.375,
                70.0,
                -5040848.5,
                -3893902.75,
                327490.625,
                71.0,
                -5038000.5,
                -3897181.0,
                332256.65625,
                72.0,
                -5035147.0,
                -3900455.25,
                337022.53125,
                73.0,
                -5032289.0,
                -3903725.0,
                341788.1875,
                74.0,
                -5029425.5,
                -3906990.5,
                346553.65625,
                75.0,
                -5026557.5,
                -3910251.75,
                351317.84375,
                76.0,
                -5023684.5,
                -3913508.75,
                356081.84375,
                77.0,
                -5020807.5,
                -3916760.25,
                360845.625,
                78.0,
                -5017992.5,
                -3919921.75,
                365609.21875,
                79.0,
                -5015105.0,
                -3923165.75,
                370372.59375,
                80.0,
                -5012212.0,
                -3926405.5,
                375134.6875,
                81.0,
                -5009314.5,
                -3929641.0,
                379897.65625,
                82.0,
                -5006413.0,
                -3932870.75,
                384659.28125,
                83.0,
                -5003506.0,
                -3936097.5,
                389420.71875,
                84.0,
                -5000593.5,
                -3939320.0,
                394180.875,
                85.0,
                -4997676.5,
                -3942538.25,
                398941.875,
                86.0,
                -4994754.5,
                -3945752.0,
                403701.53125,
                87.0,
                -4991828.0,
                -3948961.25,
                408461.0,
                88.0,
                -4988896.5,
                -3952166.25,
                413220.21875,
                89.0,
                -4985960.0,
                -3955367.0,
                417979.21875,
                90.0,
                -4983088.0,
                -3958475.5,
                422738.0,
                91.0,
                -4980142.0,
                -3961667.5,
                427495.4375,
                92.0,
                -4977191.0,
                -3964855.0,
                432252.625,
                93.0,
                -4974235.0,
                -3968038.0,
                437009.59375,
                94.0,
                -4971274.5,
                -3971216.75,
                441765.1875,
                95.0,
                -4968309.5,
                -3974391.0,
                446521.65625,
                96.0,
                -4965339.0,
                -3977560.75,
                451276.78125,
                97.0,
                -4962365.0,
                -3980725.0,
                456031.625,
                98.0,
                -4959385.5,
                -3983886.0,
                460785.15625,
                99.0,
                -4956401.0,
                -3987042.5,
                465539.5,
                100.0,
                -4953412.0,
                -3990194.5,
                470292.5,
                101.0,
                -4950417.5,
                -3993342.25,
                475045.21875,
                102.0,
                -4947419.0,
                -3996485.25,
                479797.71875,
                103.0,
                -4944415.5,
                -3999624.0,
                484548.8125,
                104.0,
                -4941407.0,
                -4002758.25,
                489299.625,
                105.0,
                -4938394.0,
                -4005888.0,
                494050.1875,
                106.0,
                -4935376.5,
                -4009013.25,
                498800.5,
                107.0,
                -4932354.0,
                -4012134.0,
                503550.5,
                108.0,
                -4929327.5,
                -4015249.0,
                508299.125,
                109.0,
                -4926296.0,
                -4018360.75,
                513047.5,
                110.0,
                -4923259.0,
                -4021468.0,
                517795.53125,
                111.0,
                -4920218.0,
                -4024570.75,
                522542.21875,
                112.0,
                -4917172.0,
                -4027669.0,
                527288.625,
                113.0,
                -4914121.5,
                -4030762.75,
                532034.6875,
                114.0,
                -4910996.0,
                -4033937.0,
                536780.5,
                115.0,
                -4907936.0,
                -4037021.5,
                541524.9375,
                116.0,
                -4904871.5,
                -4040101.5,
                546269.0,
                117.0,
                -4901802.0,
                -4043177.0,
                551012.75,
                118.0,
                -4898728.5,
                -4046248.0,
                555755.1875,
                119.0,
                -4895649.5,
                -4049314.25,
                560498.375,
                120.0,
                -4892566.5,
                -4052376.0,
                565239.0,
                121.0,
                -4889478.5,
                -4055433.25,
                569980.5,
                122.0,
                -4886386.0,
                -4058485.75,
                574720.5625,
                123.0,
                -4883289.0,
                -4061533.75,
                579460.3125,
                124.0,
                -4880188.5,
                -4064576.0,
                584199.6875,
                125.0,
                -4877010.5,
                -4067700.5,
                588938.8125,
                126.0,
                -4873899.5,
                -4070734.5,
                593676.4375,
                127.0,
                -4870784.5,
                -4073764.25,
                598413.75,
                128.0,
                -4867664.5,
                -4076789.0,
                603149.625,
                129.0,
                -4864541.0,
                -4079808.25,
                607885.1875,
                130.0,
                -4861411.5,
                -4082823.75,
                612620.4375,
                131.0,
                -4858278.0,
                -4085834.75,
                617355.3125,
                132.0,
                -4855068.0,
                -4088926.5,
                622088.75,
                133.0,
                -4851925.0,
                -4091928.25,
                626821.875,
                134.0,
                -4848777.5,
                -4094925.25,
                631554.625,
                135.0,
                -4845627.0,
                -4097916.5,
                636285.9375,
                136.0,
                -4842470.5,
                -4100904.0,
                641016.875,
                137.0,
                -4839237.5,
                -4103972.25,
                645746.4375,
                138.0,
                -4836072.0,
                -4106950.5,
                650476.625,
                139.0,
                -4832902.0,
                -4109924.25,
                655205.4375,
                140.0,
                -4829727.5,
                -4112893.25,
                659932.75,
                141.0,
                -4826550.0,
                -4115856.0,
                664659.75,
                142.0,
                -4823294.0,
                -4118900.5,
                669386.3125,
                143.0,
                -4820106.5,
                -4121855.25,
                674112.5625,
                144.0,
                -4816914.0,
                -4124805.25,
                678837.3125,
                145.0,
                -4813717.5,
                -4127750.75,
                683561.6875,
                146.0,
                -4810445.0,
                -4130774.5,
                688284.5625,
                147.0,
                -4807239.0,
                -4133710.5,
                693008.1875,
                148.0,
                -4804029.0,
                -4136641.5,
                697729.25,
                149.0,
                -4800814.5,
                -4139568.0,
                702451.0,
                150.0,
                -4797524.0,
                -4142572.75,
                707171.3125,
                151.0,
                -4794300.5,
                -4145489.5,
                711891.125,
                152.0,
                -4791073.0,
                -4148401.5,
                716609.5625,
                153.0,
                -4787769.0,
                -4151391.75,
                721327.5625,
                154.0,
                -4784532.5,
                -4154294.25,
                726044.0625,
                155.0,
                -4781291.5,
                -4157192.0,
                730761.25,
                156.0,
                -4777973.5,
                -4160169.0,
                735475.875,
                157.0,
                -4774723.5,
                -4163057.25,
                740191.1875,
                158.0,
                -4771471.0,
                -4165939.25,
                744904.9375,
                159.0,
                -4768139.5,
                -4168901.5,
                749617.25,
                160.0,
                -4764876.5,
                -4171775.25,
                754330.1875,
                161.0,
                -4761609.5,
                -4174644.0,
                759041.6875,
                162.0,
                -4758266.0,
                -4177590.5,
                763751.5625,
                163.0,
                -4754990.5,
                -4180449.75,
                768461.125,
                164.0,
                -4751638.0,
                -4183386.5,
                773170.1875,
                165.0,
                -4748353.5,
                -4186236.0,
                777877.8125,
                166.0,
                -4745065.0,
                -4189080.75,
                782584.9375,
                167.0,
                -4741698.5,
                -4192004.0,
                787290.5625,
                168.0,
                -4738401.5,
                -4194839.0,
                791995.75,
                169.0,
                -4735027.5,
                -4197751.0,
                796700.5,
                170.0,
                -4731721.5,
                -4200576.0,
                801403.6875,
                171.0,
                -4728339.0,
                -4203478.5,
                806106.5,
                172.0,
                -4725025.0,
                -4206293.5,
                810807.75,
                173.0,
                -4721632.5,
                -4209187.5,
                815508.5,
                174.0,
                -4718309.5,
                -4211993.0,
                820207.75,
                175.0,
                -4714910.0,
                -4214875.5,
                824906.5625,
                176.0,
                -4711578.5,
                -4217671.0,
                829604.9375,
                177.0,
                -4708170.5,
                -4220543.5,
                834301.75,
                178.0,
                -4704830.5,
                -4223329.5,
                838998.0625,
                179.0,
                -4701412.5,
                -4226193.5,
                843692.875,
                180.0,
                -4698064.5,
                -4228969.5,
                848387.1875,
                181.0,
                -4694639.0,
                -4231822.0,
                853081.0,
                182.0,
                -4691283.0,
                -4234588.5,
                857772.25,
                183.0,
                -4687849.0,
                -4237430.5,
                862464.0625,
                184.0,
                -4684484.5,
                -4240187.0,
                867154.3125,
                185.0,
                -4681041.0,
                -4243021.0,
                871844.0625,
                186.0,
                -4677594.5,
                -4245848.0,
                876532.3125,
                187.0,
                -4674217.5,
                -4248590.0,
                881218.9375,
                188.0,
                -4670761.5,
                -4251408.5,
                885906.125,
                189.0,
                -4667376.5,
                -4254140.0,
                890590.75,
                190.0,
                -4663913.0,
                -4256947.0,
                895275.9375,
                191.0,
                -4660446.0,
                -4259749.5,
                899958.5,
                192.0,
                -4657048.5,
                -4262466.0,
                904641.5625,
                193.0,
                -4653571.5,
                -4265259.5,
                909322.0,
                194.0,
                -4650092.0,
                -4268046.5,
                914002.9375,
                195.0,
                -4646682.0,
                -4270748.0,
                918682.375,
                196.0,
                -4643193.0,
                -4273526.0,
                923360.25,
                197.0,
                -4639701.0,
                -4276298.0,
                928037.625,
                198.0,
                -4636279.0,
                -4278984.5,
                932713.3125,
                199.0,
                -4632778.5,
                -4281746.0,
                937388.5
            ]
        },
        "cylinder": {
            "length": 1400000.0,
            "topRadius": 0,
            "bottomRadius": 412116.1825368106,
            "material": {
                "solidColor": {
                    "color": {
                        "rgba": [
                            19.0,
                            206.0,
                            102.0,
                            204.0
                        ]
                    }
                }
            }
        }
    }
]