{
    "id": 1316,
    "name": 1316,
    "availability": "2000-01-01T00:00:00.000Z/2000-01-01T00:16:40.000Z",
    "description": "",
    "position": {
        "interpolationAlgorithm": "LAGRANGE",
        "interpolationDegree": 5,
        "referenceFrame": "FIXED",
        "epoch": "2000-01-01T00:00:00.000Z",
        "cartesian": [
            0.0,
            -3763590.0,
            2924060.0,
            -5039370.0,
            5960.0,
            -3649700.0,
            3985880.0,
            -4347170.0,
            5970.0,
            -3710120.0,
            3971060.0,
            -4309400.0,
            5980.0,
            -3770120.0,
            3955850.0,
            -4271110.0,
            5990.0,
            -3829690.0,
            3940260.0,
            -4232310.0,
            10.0,
            -3822930.0,
            2890540.0,
            -5013960.0,
            20.0,
            -3881860.0,
            2856760.0,
            -4987950.0,
            30.0,
            -3940390.0,
            2822730.0,
            -4961350.0,
            40.0,
            -3998500.0,
            2788450.0,
            -4934150.0,
            50.0,
            -4056180.0,
            2753920.0,
            -4906370.0,
            60.0,
            -4113430.0,
            2719150.0,
            -4878000.0,
            70.0,
            -4170250.0,
            2684140.0,
            -4849040.0,
            80.0,
            -4226620.0,
            2648890.0,
            -4819510.0,
            90.0,
            -4282540.0,
            2613420.0,
            -4789400.0,
            100.0,
            -4338010.0,
            2577710.0,
            -4758710.0,
            110.0,
            -4393010.0,
            2541770.0,
            -4727460.0,
            120.0,
            -4447540.0,
            2505620.0,
            -4695650.0,
            130.0,
            -4501600.0,
            2469240.0,
            -4663270.0,
            140.0,
            -4555180.0,
            2432660.0,
            -4630330.0,
            150.0,
            -4608270.0,
            2395860.0,
            -4596840.0,
            160.0,
            -4660860.0,
            2358850.0,
            -4562800.0,
            170.0,
            -4712960.0,
            2321640.0,
            -4528210.0,
            180.0,
            -4764550.0,
            2284230.0,
            -4493090.0,
            190.0,
            -4815630.0,
            2246620.0,
            -4457420.0,
            200.0,
            -4866200.0,
            2208820.0,
            -4421220.0,
            210.0,
            -4916240.0,
            2170830.0,
            -4384500.0,
            220.0,
            -4965750.0,
            2132660.0,
            -4347250.0,
            230.0,
            -5014730.0,
            2094310.0,
            -4309480.0,
            240.0,
            -5063170.0,
            2055770.0,
            -4271190.0,
            250.0,
            -5111060.0,
            2017070.0,
            -4232390.0,
            260.0,
            -5158410.0,
            1978190.0,
            -4193090.0,
            270.0,
            -5205200.0,
            1939150.0,
            -4153280.0,
            280.0,
            -5251420.0,
            1899940.0,
            -4112980.0,
            290.0,
            -5297080.0,
            1860570.0,
            -4072180.0,
            300.0,
            -5342170.0,
            1821060.0,
            -4030900.0,
            310.0,
            -5386680.0,
            1781380.0,
            -3989130.0,
            320.0,
            -5430610.0,
            1741570.0,
            -3946890.0,
            330.0,
            -5473950.0,
            1701610.0,
            -3904180.0,
            340.0,
            -5516700.0,
            1661500.0,
            -3860990.0,
            350.0,
            -5558850.0,
            1621270.0,
            -3817350.0,
            360.0,
            -5600400.0,
            1580900.0,
            -3773250.0,
            370.0,
            -5641350.0,
            1540400.0,
            -3728690.0,
            380.0,
            -5681680.0,
            1499790.0,
            -3683690.0,
            390.0,
            -5721390.0,
            1459050.0,
            -3638250.0,
            400.0,
            -5760490.0,
            1418190.0,
            -3592380.0,
            410.0,
            -5798960.0,
            1377220.0,
            -3546070.0,
            420.0,
            -5836800.0,
            1336150.0,
            -3499340.0,
            430.0,
            -5874000.0,
            1294970.0,
            -3452190.0,
            440.0,
            -5910570.0,
            1253690.0,
            -3404620.0,
            450.0,
            -5946500.0,
            1212310.0,
            -3356650.0,
            460.0,
            -5981780.0,
            1170840.0,
            -3308280.0,
            470.0,
            -6016400.0,
            1129290.0,
            -3259510.0,
            480.0,
            -6050370.0,
            1087640.0,
            -3210350.0,
            490.0,
            -6083690.0,
            1045920.0,
            -3160800.0,
            500.0,
            -6116340.0,
            1004130.0,
            -3110880.0,
            510.0,
            -6148320.0,
            962256.0,
            -3060580.0,
            520.0,
            -6179640.0,
            920317.0,
            -3009910.0,
            530.0,
            -6210270.0,
            878314.0,
            -2958890.0,
            540.0,
            -6240240.0,
            836251.0,
            -2907510.0,
            550.0,
            -6269520.0,
            794132.0,
            -2855780.0,
            560.0,
            -6298110.0,
            751960.0,
            -2803710.0,
            570.0,
            -6326020.0,
            709741.0,
            -2751310.0,
            580.0,
            -6353240.0,
            667476.0,
            -2698570.0,
            590.0,
            -6379760.0,
            625172.0,
            -2645510.0,
            600.0,
            -6405580.0,
            582831.0,
            -2592130.0,
            610.0,
            -6430710.0,
            540458.0,
            -2538450.0,
            620.0,
            -6455130.0,
            498057.0,
            -2484450.0,
            630.0,
            -6478840.0,
            455632.0,
            -2430160.0,
            640.0,
            -6501840.0,
            413186.0,
            -2375580.0,
            650.0,
            -6524140.0,
            370724.0,
            -2320720.0,
            660.0,
            -6545710.0,
            328251.0,
            -2265570.0,
            670.0,
            -6566570.0,
            285769.0,
            -2210160.0,
            680.0,
            -6586710.0,
            243282.0,
            -2154470.0,
            690.0,
            -6606130.0,
            200796.0,
            -2098530.0,
            700.0,
            -6624820.0,
            158314.0,
            -2042340.0,
            710.0,
            -6642780.0,
            115839.0,
            -1985910.0,
            720.0,
            -6660020.0,
            73376.6015625,
            -1929230.0,
            730.0,
            -6676520.0,
            30929.80078125,
            -1872330.0,
            740.0,
            -6692290.0,
            -11497.2001953125,
            -1815190.0,
            750.0,
            -6707330.0,
            -53900.30078125,
            -1757850.0,
            760.0,
            -6721630.0,
            -96275.6015625,
            -1700290.0,
            770.0,
            -6735190.0,
            -138619.0,
            -1642520.0,
            780.0,
            -6748000.0,
            -180927.0,
            -1584560.0,
            790.0,
            -6760080.0,
            -223195.0,
            -1526410.0,
            800.0,
            -6771410.0,
            -265419.0,
            -1468080.0,
            810.0,
            -6782000.0,
            -307596.0,
            -1409570.0,
            820.0,
            -6791840.0,
            -349721.0,
            -1350890.0,
            830.0,
            -6800930.0,
            -391791.0,
            -1292050.0,
            840.0,
            -6809270.0,
            -433801.0,
            -1233050.0,
            850.0,
            -6816860.0,
            -475748.0,
            -1173900.0,
            860.0,
            -6823700.0,
            -517628.0,
            -1114620.0,
            870.0,
            -6829790.0,
            -559437.0,
            -1055200.0,
            880.0,
            -6835130.0,
            -601171.0,
            -995652.0,
            890.0,
            -6839710.0,
            -642825.0,
            -935987.0,
            900.0,
            -6843540.0,
            -684397.0,
            -876208.0,
            910.0,
            -6846610.0,
            -725883.0,
            -816325.0,
            920.0,
            -6848920.0,
            -767278.0,
            -756344.0,
            930.0,
            -6850480.0,
            -808578.0,
            -696271.0,
            940.0,
            -6851280.0,
            -849781.0,
            -636115.0,
            950.0,
            -6851330.0,
            -890881.0,
            -575883.0,
            960.0,
            -6850620.0,
            -931876.0,
            -515582.0,
            970.0,
            -6849150.0,
            -972761.0,
            -455218.0,
            980.0,
            -6846920.0,
            -1013530.0,
            -394800.0,
            990.0,
            -6843940.0,
            -1054190.0,
            -334335.0
        ]
    },
    "point": {
        "show": true,
        "color": {
            "rgba": [
                8.0,
                227.0,
                26.0,
                255.0
            ]
        },
        "pixelSize": 7
    }
}
